{
    "scheduled_programs": [
        {
            "program_id": "Frontiers of Infinity_program_0",
            "channel_id": 8,
            "start": 1247,
            "end": 1281
        },
        {
            "program_id": "Frontiers of Infinity_program_1",
            "channel_id": 8,
            "start": 1281,
            "end": 1311
        },
        {
            "program_id": "Crux_program_1",
            "channel_id": 0,
            "start": 1311,
            "end": 1343
        },
        {
            "program_id": "Crux_program_2",
            "channel_id": 0,
            "start": 1343,
            "end": 1373
        },
        {
            "program_id": "afarTV_program_1",
            "channel_id": 6,
            "start": 1373,
            "end": 1403
        },
        {
            "program_id": "afarTV_program_2",
            "channel_id": 6,
            "start": 1403,
            "end": 1435
        },
        {
            "program_id": "Sen_program_3",
            "channel_id": 2,
            "start": 1435,
            "end": 1465
        },
        {
            "program_id": "Frontiers of Infinity_program_3",
            "channel_id": 8,
            "start": 1465,
            "end": 1504
        },
        {
            "program_id": "Frontiers of Infinity_program_4",
            "channel_id": 8,
            "start": 1504,
            "end": 1534
        },
        {
            "program_id": "Dream Trips_program_4",
            "channel_id": 3,
            "start": 1535,
            "end": 1574
        },
        {
            "program_id": "afarTV_program_4",
            "channel_id": 6,
            "start": 1574,
            "end": 1608
        },
        {
            "program_id": "afarTV_program_5",
            "channel_id": 6,
            "start": 1608,
            "end": 1638
        },
        {
            "program_id": "The Financial Express_program_6",
            "channel_id": 1,
            "start": 1638,
            "end": 1669
        },
        {
            "program_id": "The Financial Express_program_7",
            "channel_id": 1,
            "start": 1669,
            "end": 1699
        },
        {
            "program_id": "afarTV_program_6",
            "channel_id": 6,
            "start": 1699,
            "end": 1745
        },
        {
            "program_id": "afarTV_program_7",
            "channel_id": 6,
            "start": 1745,
            "end": 1775
        },
        {
            "program_id": "Sen_program_8",
            "channel_id": 2,
            "start": 1779,
            "end": 1810
        },
        {
            "program_id": "Sen_program_9",
            "channel_id": 2,
            "start": 1810,
            "end": 1845
        },
        {
            "program_id": "NASA_program_10",
            "channel_id": 4,
            "start": 1845,
            "end": 1879
        },
        {
            "program_id": "NASA_program_11",
            "channel_id": 4,
            "start": 1879,
            "end": 1909
        },
        {
            "program_id": "Crux_program_12",
            "channel_id": 0,
            "start": 1921,
            "end": 1959
        }
    ]
}