{
  "opening_time": 1034,
  "closing_time": 1430,
  "min_duration": 30,
  "max_consecutive_genre": 10,
  "channels_count": 10,
  "switch_penalty": 9,
  "termination_penalty": 20,
  "priority_blocks": [],
  "time_preferences": [
    {
      "start": 480,
      "end": 720,
      "preferred_genre": "technology",
      "bonus": 5
    },
    {
      "start": 720,
      "end": 960,
      "preferred_genre": "science",
      "bonus": 5
    },
    {
      "start": 960,
      "end": 1200,
      "preferred_genre": "climate",
      "bonus": 5
    },
    {
      "start": 1200,
      "end": 1440,
      "preferred_genre": "others",
      "bonus": 5
    }
  ],
  "channels": [
    {
      "channel_id": 0,
      "channel_name": "NASA Live | SpaceX Live | LIVE SpaceX Launches Two Moon Landing Missions In One Rocket | US News 2026-02-20 17:14",
      "programs": [
        {
          "program_id": "NASA Live | SpaceX Live | LIVE SpaceX Launches Two Moon Landing Missions In One Rocket | US News 2026-02-20 17:14_program_0",
          "program_name": "NASA Live | SpaceX Live | LIVE SpaceX Launches Two Moon Landing Missions In One Rocket | US News 2026-02-20 17:14",
          "start": 1034,
          "end": 1120,
          "genre": "technology",
          "score": 82,
          "url": "https://www.youtube.com/watch?v=oXsBLbUUe3c"
        },
        {
          "program_id": "NASA Live | SpaceX Live | LIVE SpaceX Launches Two Moon Landing Missions In One Rocket | US News 2026-02-20 17:14_program_1",
          "program_name": "NASA Live | SpaceX Live | LIVE SpaceX Launches Two Moon Landing Missions In One Rocket | US News 2026-02-20 17:14",
          "start": 1120,
          "end": 1199,
          "genre": "technology",
          "score": 79,
          "url": "https://www.youtube.com/watch?v=oXsBLbUUe3c"
        },
        {
          "program_id": "NASA Live | SpaceX Live | LIVE SpaceX Launches Two Moon Landing Missions In One Rocket | US News 2026-02-20 17:14_program_2",
          "program_name": "NASA Live | SpaceX Live | LIVE SpaceX Launches Two Moon Landing Missions In One Rocket | US News 2026-02-20 17:14",
          "start": 1199,
          "end": 1288,
          "genre": "technology",
          "score": 87,
          "url": "https://www.youtube.com/watch?v=oXsBLbUUe3c"
        },
        {
          "program_id": "NASA Live | SpaceX Live | LIVE SpaceX Launches Two Moon Landing Missions In One Rocket | US News 2026-02-20 17:14_program_3",
          "program_name": "NASA Live | SpaceX Live | LIVE SpaceX Launches Two Moon Landing Missions In One Rocket | US News 2026-02-20 17:14",
          "start": 1288,
          "end": 1353,
          "genre": "technology",
          "score": 92,
          "url": "https://www.youtube.com/watch?v=oXsBLbUUe3c"
        },
        {
          "program_id": "NASA Live | SpaceX Live | LIVE SpaceX Launches Two Moon Landing Missions In One Rocket | US News 2026-02-20 17:14_program_4",
          "program_name": "NASA Live | SpaceX Live | LIVE SpaceX Launches Two Moon Landing Missions In One Rocket | US News 2026-02-20 17:14",
          "start": 1353,
          "end": 1430,
          "genre": "technology",
          "score": 79,
          "url": "https://www.youtube.com/watch?v=oXsBLbUUe3c"
        }
      ]
    },
    {
      "channel_id": 1,
      "channel_name": "NASA Live: SpaceX Makes History With Dual Moon Missions Launch | SpaceX Live | US News 2026-02-20 17:14",
      "programs": [
        {
          "program_id": "NASA Live: SpaceX Makes History With Dual Moon Missions Launch | SpaceX Live | US News 2026-02-20 17:14_program_0",
          "program_name": "NASA Live: SpaceX Makes History With Dual Moon Missions Launch | SpaceX Live | US News 2026-02-20 17:14",
          "start": 1034,
          "end": 1086,
          "genre": "technology",
          "score": 78,
          "url": "https://www.youtube.com/watch?v=Gh1Mt4BSo6Y"
        },
        {
          "program_id": "NASA Live: SpaceX Makes History With Dual Moon Missions Launch | SpaceX Live | US News 2026-02-20 17:14_program_1",
          "program_name": "NASA Live: SpaceX Makes History With Dual Moon Missions Launch | SpaceX Live | US News 2026-02-20 17:14",
          "start": 1086,
          "end": 1134,
          "genre": "technology",
          "score": 84,
          "url": "https://www.youtube.com/watch?v=Gh1Mt4BSo6Y"
        },
        {
          "program_id": "NASA Live: SpaceX Makes History With Dual Moon Missions Launch | SpaceX Live | US News 2026-02-20 17:14_program_2",
          "program_name": "NASA Live: SpaceX Makes History With Dual Moon Missions Launch | SpaceX Live | US News 2026-02-20 17:14",
          "start": 1134,
          "end": 1190,
          "genre": "technology",
          "score": 78,
          "url": "https://www.youtube.com/watch?v=Gh1Mt4BSo6Y"
        },
        {
          "program_id": "NASA Live: SpaceX Makes History With Dual Moon Missions Launch | SpaceX Live | US News 2026-02-20 17:14_program_3",
          "program_name": "NASA Live: SpaceX Makes History With Dual Moon Missions Launch | SpaceX Live | US News 2026-02-20 17:14",
          "start": 1190,
          "end": 1278,
          "genre": "technology",
          "score": 80,
          "url": "https://www.youtube.com/watch?v=Gh1Mt4BSo6Y"
        },
        {
          "program_id": "NASA Live: SpaceX Makes History With Dual Moon Missions Launch | SpaceX Live | US News 2026-02-20 17:14_program_4",
          "program_name": "NASA Live: SpaceX Makes History With Dual Moon Missions Launch | SpaceX Live | US News 2026-02-20 17:14",
          "start": 1278,
          "end": 1353,
          "genre": "technology",
          "score": 85,
          "url": "https://www.youtube.com/watch?v=Gh1Mt4BSo6Y"
        },
        {
          "program_id": "NASA Live: SpaceX Makes History With Dual Moon Missions Launch | SpaceX Live | US News 2026-02-20 17:14_program_5",
          "program_name": "NASA Live: SpaceX Makes History With Dual Moon Missions Launch | SpaceX Live | US News 2026-02-20 17:14",
          "start": 1353,
          "end": 1395,
          "genre": "technology",
          "score": 76,
          "url": "https://www.youtube.com/watch?v=Gh1Mt4BSo6Y"
        },
        {
          "program_id": "NASA Live: SpaceX Makes History With Dual Moon Missions Launch | SpaceX Live | US News 2026-02-20 17:14_program_6",
          "program_name": "NASA Live: SpaceX Makes History With Dual Moon Missions Launch | SpaceX Live | US News 2026-02-20 17:14",
          "start": 1395,
          "end": 1430,
          "genre": "technology",
          "score": 88,
          "url": "https://www.youtube.com/watch?v=Gh1Mt4BSo6Y"
        }
      ]
    },
    {
      "channel_id": 2,
      "channel_name": "Live 4K video of Earth and space: 24/7 Livestream of Earth by Sen\u2019s 4K video cameras on the ISS 2026-02-20 17:14",
      "programs": [
        {
          "program_id": "Live 4K video of Earth and space: 24/7 Livestream of Earth by Sen\u2019s 4K video cameras on the ISS 2026-02-20 17:14_program_0",
          "program_name": "Live 4K video of Earth and space: 24/7 Livestream of Earth by Sen\u2019s 4K video cameras on the ISS 2026-02-20 17:14",
          "start": 1034,
          "end": 1066,
          "genre": "technology",
          "score": 93,
          "url": "https://www.youtube.com/watch?v=fO9e9jnhYK8"
        },
        {
          "program_id": "Live 4K video of Earth and space: 24/7 Livestream of Earth by Sen\u2019s 4K video cameras on the ISS 2026-02-20 17:14_program_1",
          "program_name": "Live 4K video of Earth and space: 24/7 Livestream of Earth by Sen\u2019s 4K video cameras on the ISS 2026-02-20 17:14",
          "start": 1066,
          "end": 1148,
          "genre": "technology",
          "score": 75,
          "url": "https://www.youtube.com/watch?v=fO9e9jnhYK8"
        },
        {
          "program_id": "Live 4K video of Earth and space: 24/7 Livestream of Earth by Sen\u2019s 4K video cameras on the ISS 2026-02-20 17:14_program_2",
          "program_name": "Live 4K video of Earth and space: 24/7 Livestream of Earth by Sen\u2019s 4K video cameras on the ISS 2026-02-20 17:14",
          "start": 1148,
          "end": 1237,
          "genre": "technology",
          "score": 84,
          "url": "https://www.youtube.com/watch?v=fO9e9jnhYK8"
        },
        {
          "program_id": "Live 4K video of Earth and space: 24/7 Livestream of Earth by Sen\u2019s 4K video cameras on the ISS 2026-02-20 17:14_program_3",
          "program_name": "Live 4K video of Earth and space: 24/7 Livestream of Earth by Sen\u2019s 4K video cameras on the ISS 2026-02-20 17:14",
          "start": 1237,
          "end": 1317,
          "genre": "technology",
          "score": 82,
          "url": "https://www.youtube.com/watch?v=fO9e9jnhYK8"
        },
        {
          "program_id": "Live 4K video of Earth and space: 24/7 Livestream of Earth by Sen\u2019s 4K video cameras on the ISS 2026-02-20 17:14_program_4",
          "program_name": "Live 4K video of Earth and space: 24/7 Livestream of Earth by Sen\u2019s 4K video cameras on the ISS 2026-02-20 17:14",
          "start": 1317,
          "end": 1405,
          "genre": "technology",
          "score": 85,
          "url": "https://www.youtube.com/watch?v=fO9e9jnhYK8"
        }
      ]
    },
    {
      "channel_id": 3,
      "channel_name": "NASA Cameras Just Caught This on the ISS Live Feed 2026-02-20 17:15",
      "programs": [
        {
          "program_id": "NASA Cameras Just Caught This on the ISS Live Feed 2026-02-20 17:15_program_0",
          "program_name": "NASA Cameras Just Caught This on the ISS Live Feed 2026-02-20 17:15",
          "start": 1034,
          "end": 1122,
          "genre": "technology",
          "score": 92,
          "url": "https://www.youtube.com/watch?v=kWRhLLbLFE0"
        },
        {
          "program_id": "NASA Cameras Just Caught This on the ISS Live Feed 2026-02-20 17:15_program_1",
          "program_name": "NASA Cameras Just Caught This on the ISS Live Feed 2026-02-20 17:15",
          "start": 1122,
          "end": 1209,
          "genre": "technology",
          "score": 82,
          "url": "https://www.youtube.com/watch?v=kWRhLLbLFE0"
        },
        {
          "program_id": "NASA Cameras Just Caught This on the ISS Live Feed 2026-02-20 17:15_program_2",
          "program_name": "NASA Cameras Just Caught This on the ISS Live Feed 2026-02-20 17:15",
          "start": 1209,
          "end": 1278,
          "genre": "technology",
          "score": 75,
          "url": "https://www.youtube.com/watch?v=kWRhLLbLFE0"
        },
        {
          "program_id": "NASA Cameras Just Caught This on the ISS Live Feed 2026-02-20 17:15_program_3",
          "program_name": "NASA Cameras Just Caught This on the ISS Live Feed 2026-02-20 17:15",
          "start": 1278,
          "end": 1347,
          "genre": "technology",
          "score": 80,
          "url": "https://www.youtube.com/watch?v=kWRhLLbLFE0"
        },
        {
          "program_id": "NASA Cameras Just Caught This on the ISS Live Feed 2026-02-20 17:15_program_4",
          "program_name": "NASA Cameras Just Caught This on the ISS Live Feed 2026-02-20 17:15",
          "start": 1347,
          "end": 1401,
          "genre": "technology",
          "score": 77,
          "url": "https://www.youtube.com/watch?v=kWRhLLbLFE0"
        }
      ]
    },
    {
      "channel_id": 4,
      "channel_name": "NASA's Artemis II Live Views from Kennedy Space Center 2026-02-20 17:15",
      "programs": [
        {
          "program_id": "NASA's Artemis II Live Views from Kennedy Space Center 2026-02-20 17:15_program_0",
          "program_name": "NASA's Artemis II Live Views from Kennedy Space Center 2026-02-20 17:15",
          "start": 1034,
          "end": 1080,
          "genre": "science",
          "score": 96,
          "url": "https://www.youtube.com/watch?v=xCrPD7tfcr0"
        },
        {
          "program_id": "NASA's Artemis II Live Views from Kennedy Space Center 2026-02-20 17:15_program_1",
          "program_name": "NASA's Artemis II Live Views from Kennedy Space Center 2026-02-20 17:15",
          "start": 1080,
          "end": 1153,
          "genre": "science",
          "score": 88,
          "url": "https://www.youtube.com/watch?v=xCrPD7tfcr0"
        },
        {
          "program_id": "NASA's Artemis II Live Views from Kennedy Space Center 2026-02-20 17:15_program_2",
          "program_name": "NASA's Artemis II Live Views from Kennedy Space Center 2026-02-20 17:15",
          "start": 1153,
          "end": 1207,
          "genre": "science",
          "score": 100,
          "url": "https://www.youtube.com/watch?v=xCrPD7tfcr0"
        },
        {
          "program_id": "NASA's Artemis II Live Views from Kennedy Space Center 2026-02-20 17:15_program_3",
          "program_name": "NASA's Artemis II Live Views from Kennedy Space Center 2026-02-20 17:15",
          "start": 1207,
          "end": 1266,
          "genre": "science",
          "score": 86,
          "url": "https://www.youtube.com/watch?v=xCrPD7tfcr0"
        },
        {
          "program_id": "NASA's Artemis II Live Views from Kennedy Space Center 2026-02-20 17:15_program_4",
          "program_name": "NASA's Artemis II Live Views from Kennedy Space Center 2026-02-20 17:15",
          "start": 1266,
          "end": 1336,
          "genre": "science",
          "score": 95,
          "url": "https://www.youtube.com/watch?v=xCrPD7tfcr0"
        },
        {
          "program_id": "NASA's Artemis II Live Views from Kennedy Space Center 2026-02-20 17:15_program_5",
          "program_name": "NASA's Artemis II Live Views from Kennedy Space Center 2026-02-20 17:15",
          "start": 1336,
          "end": 1424,
          "genre": "science",
          "score": 105,
          "url": "https://www.youtube.com/watch?v=xCrPD7tfcr0"
        }
      ]
    },
    {
      "channel_id": 5,
      "channel_name": "Space Coast Live: 24/7 Views of NASA, SpaceX Falcon 9 Operations, and Starship Pad Construction 2026-02-20 17:15",
      "programs": [
        {
          "program_id": "Space Coast Live: 24/7 Views of NASA, SpaceX Falcon 9 Operations, and Starship Pad Construction 2026-02-20 17:15_program_0",
          "program_name": "Space Coast Live: 24/7 Views of NASA, SpaceX Falcon 9 Operations, and Starship Pad Construction 2026-02-20 17:15",
          "start": 1034,
          "end": 1091,
          "genre": "science",
          "score": 89,
          "url": "https://www.youtube.com/watch?v=Jm8wRjD3xVA"
        },
        {
          "program_id": "Space Coast Live: 24/7 Views of NASA, SpaceX Falcon 9 Operations, and Starship Pad Construction 2026-02-20 17:15_program_1",
          "program_name": "Space Coast Live: 24/7 Views of NASA, SpaceX Falcon 9 Operations, and Starship Pad Construction 2026-02-20 17:15",
          "start": 1091,
          "end": 1173,
          "genre": "science",
          "score": 96,
          "url": "https://www.youtube.com/watch?v=Jm8wRjD3xVA"
        },
        {
          "program_id": "Space Coast Live: 24/7 Views of NASA, SpaceX Falcon 9 Operations, and Starship Pad Construction 2026-02-20 17:15_program_2",
          "program_name": "Space Coast Live: 24/7 Views of NASA, SpaceX Falcon 9 Operations, and Starship Pad Construction 2026-02-20 17:15",
          "start": 1173,
          "end": 1234,
          "genre": "science",
          "score": 103,
          "url": "https://www.youtube.com/watch?v=Jm8wRjD3xVA"
        },
        {
          "program_id": "Space Coast Live: 24/7 Views of NASA, SpaceX Falcon 9 Operations, and Starship Pad Construction 2026-02-20 17:15_program_3",
          "program_name": "Space Coast Live: 24/7 Views of NASA, SpaceX Falcon 9 Operations, and Starship Pad Construction 2026-02-20 17:15",
          "start": 1234,
          "end": 1310,
          "genre": "science",
          "score": 101,
          "url": "https://www.youtube.com/watch?v=Jm8wRjD3xVA"
        },
        {
          "program_id": "Space Coast Live: 24/7 Views of NASA, SpaceX Falcon 9 Operations, and Starship Pad Construction 2026-02-20 17:15_program_4",
          "program_name": "Space Coast Live: 24/7 Views of NASA, SpaceX Falcon 9 Operations, and Starship Pad Construction 2026-02-20 17:15",
          "start": 1310,
          "end": 1390,
          "genre": "science",
          "score": 91,
          "url": "https://www.youtube.com/watch?v=Jm8wRjD3xVA"
        },
        {
          "program_id": "Space Coast Live: 24/7 Views of NASA, SpaceX Falcon 9 Operations, and Starship Pad Construction 2026-02-20 17:15_program_5",
          "program_name": "Space Coast Live: 24/7 Views of NASA, SpaceX Falcon 9 Operations, and Starship Pad Construction 2026-02-20 17:15",
          "start": 1390,
          "end": 1424,
          "genre": "science",
          "score": 103,
          "url": "https://www.youtube.com/watch?v=Jm8wRjD3xVA"
        }
      ]
    },
    {
      "channel_id": 6,
      "channel_name": "\ud83d\udd34 Live Now: 24/7 NASA Live Stream of Earth from Space (ISS) 2026-02-20 17:15",
      "programs": [
        {
          "program_id": "\ud83d\udd34 Live Now: 24/7 NASA Live Stream of Earth from Space (ISS) 2026-02-20 17:15_program_0",
          "program_name": "\ud83d\udd34 Live Now: 24/7 NASA Live Stream of Earth from Space (ISS) 2026-02-20 17:15",
          "start": 1034,
          "end": 1085,
          "genre": "science",
          "score": 89,
          "url": "https://www.youtube.com/watch?v=vytmBNhc9ig"
        },
        {
          "program_id": "\ud83d\udd34 Live Now: 24/7 NASA Live Stream of Earth from Space (ISS) 2026-02-20 17:15_program_1",
          "program_name": "\ud83d\udd34 Live Now: 24/7 NASA Live Stream of Earth from Space (ISS) 2026-02-20 17:15",
          "start": 1085,
          "end": 1168,
          "genre": "science",
          "score": 98,
          "url": "https://www.youtube.com/watch?v=vytmBNhc9ig"
        },
        {
          "program_id": "\ud83d\udd34 Live Now: 24/7 NASA Live Stream of Earth from Space (ISS) 2026-02-20 17:15_program_2",
          "program_name": "\ud83d\udd34 Live Now: 24/7 NASA Live Stream of Earth from Space (ISS) 2026-02-20 17:15",
          "start": 1168,
          "end": 1246,
          "genre": "science",
          "score": 101,
          "url": "https://www.youtube.com/watch?v=vytmBNhc9ig"
        },
        {
          "program_id": "\ud83d\udd34 Live Now: 24/7 NASA Live Stream of Earth from Space (ISS) 2026-02-20 17:15_program_3",
          "program_name": "\ud83d\udd34 Live Now: 24/7 NASA Live Stream of Earth from Space (ISS) 2026-02-20 17:15",
          "start": 1246,
          "end": 1298,
          "genre": "science",
          "score": 88,
          "url": "https://www.youtube.com/watch?v=vytmBNhc9ig"
        },
        {
          "program_id": "\ud83d\udd34 Live Now: 24/7 NASA Live Stream of Earth from Space (ISS) 2026-02-20 17:15_program_4",
          "program_name": "\ud83d\udd34 Live Now: 24/7 NASA Live Stream of Earth from Space (ISS) 2026-02-20 17:15",
          "start": 1298,
          "end": 1338,
          "genre": "science",
          "score": 102,
          "url": "https://www.youtube.com/watch?v=vytmBNhc9ig"
        },
        {
          "program_id": "\ud83d\udd34 Live Now: 24/7 NASA Live Stream of Earth from Space (ISS) 2026-02-20 17:15_program_5",
          "program_name": "\ud83d\udd34 Live Now: 24/7 NASA Live Stream of Earth from Space (ISS) 2026-02-20 17:15",
          "start": 1338,
          "end": 1379,
          "genre": "science",
          "score": 103,
          "url": "https://www.youtube.com/watch?v=vytmBNhc9ig"
        },
        {
          "program_id": "\ud83d\udd34 Live Now: 24/7 NASA Live Stream of Earth from Space (ISS) 2026-02-20 17:15_program_6",
          "program_name": "\ud83d\udd34 Live Now: 24/7 NASA Live Stream of Earth from Space (ISS) 2026-02-20 17:15",
          "start": 1379,
          "end": 1427,
          "genre": "science",
          "score": 105,
          "url": "https://www.youtube.com/watch?v=vytmBNhc9ig"
        }
      ]
    },
    {
      "channel_id": 7,
      "channel_name": "International Space Station (ISS) Camera's Capture Views Of Hurricane Matthew [Unedited] 2026-02-20 17:15",
      "programs": [
        {
          "program_id": "International Space Station (ISS) Camera's Capture Views Of Hurricane Matthew [Unedited] 2026-02-20 17:15_program_0",
          "program_name": "International Space Station (ISS) Camera's Capture Views Of Hurricane Matthew [Unedited] 2026-02-20 17:15",
          "start": 1034,
          "end": 1101,
          "genre": "science",
          "score": 90,
          "url": "https://www.youtube.com/watch?v=nRkpb2NWn_4"
        },
        {
          "program_id": "International Space Station (ISS) Camera's Capture Views Of Hurricane Matthew [Unedited] 2026-02-20 17:15_program_1",
          "program_name": "International Space Station (ISS) Camera's Capture Views Of Hurricane Matthew [Unedited] 2026-02-20 17:15",
          "start": 1101,
          "end": 1157,
          "genre": "science",
          "score": 100,
          "url": "https://www.youtube.com/watch?v=nRkpb2NWn_4"
        },
        {
          "program_id": "International Space Station (ISS) Camera's Capture Views Of Hurricane Matthew [Unedited] 2026-02-20 17:15_program_2",
          "program_name": "International Space Station (ISS) Camera's Capture Views Of Hurricane Matthew [Unedited] 2026-02-20 17:15",
          "start": 1157,
          "end": 1239,
          "genre": "science",
          "score": 89,
          "url": "https://www.youtube.com/watch?v=nRkpb2NWn_4"
        },
        {
          "program_id": "International Space Station (ISS) Camera's Capture Views Of Hurricane Matthew [Unedited] 2026-02-20 17:15_program_3",
          "program_name": "International Space Station (ISS) Camera's Capture Views Of Hurricane Matthew [Unedited] 2026-02-20 17:15",
          "start": 1239,
          "end": 1310,
          "genre": "science",
          "score": 89,
          "url": "https://www.youtube.com/watch?v=nRkpb2NWn_4"
        },
        {
          "program_id": "International Space Station (ISS) Camera's Capture Views Of Hurricane Matthew [Unedited] 2026-02-20 17:15_program_4",
          "program_name": "International Space Station (ISS) Camera's Capture Views Of Hurricane Matthew [Unedited] 2026-02-20 17:15",
          "start": 1310,
          "end": 1389,
          "genre": "science",
          "score": 105,
          "url": "https://www.youtube.com/watch?v=nRkpb2NWn_4"
        },
        {
          "program_id": "International Space Station (ISS) Camera's Capture Views Of Hurricane Matthew [Unedited] 2026-02-20 17:15_program_5",
          "program_name": "International Space Station (ISS) Camera's Capture Views Of Hurricane Matthew [Unedited] 2026-02-20 17:15",
          "start": 1389,
          "end": 1430,
          "genre": "science",
          "score": 87,
          "url": "https://www.youtube.com/watch?v=nRkpb2NWn_4"
        }
      ]
    },
    {
      "channel_id": 8,
      "channel_name": "24/7 Universe, Physics & Ancient Mysteries 2026-02-20 17:15",
      "programs": [
        {
          "program_id": "24/7 Universe, Physics & Ancient Mysteries 2026-02-20 17:15_program_0",
          "program_name": "24/7 Universe, Physics & Ancient Mysteries 2026-02-20 17:15",
          "start": 1034,
          "end": 1120,
          "genre": "science",
          "score": 96,
          "url": "https://www.youtube.com/watch?v=RwQPMHZHsY0"
        },
        {
          "program_id": "24/7 Universe, Physics & Ancient Mysteries 2026-02-20 17:15_program_1",
          "program_name": "24/7 Universe, Physics & Ancient Mysteries 2026-02-20 17:15",
          "start": 1120,
          "end": 1150,
          "genre": "science",
          "score": 86,
          "url": "https://www.youtube.com/watch?v=RwQPMHZHsY0"
        },
        {
          "program_id": "24/7 Universe, Physics & Ancient Mysteries 2026-02-20 17:15_program_2",
          "program_name": "24/7 Universe, Physics & Ancient Mysteries 2026-02-20 17:15",
          "start": 1150,
          "end": 1194,
          "genre": "science",
          "score": 90,
          "url": "https://www.youtube.com/watch?v=RwQPMHZHsY0"
        },
        {
          "program_id": "24/7 Universe, Physics & Ancient Mysteries 2026-02-20 17:15_program_3",
          "program_name": "24/7 Universe, Physics & Ancient Mysteries 2026-02-20 17:15",
          "start": 1194,
          "end": 1254,
          "genre": "science",
          "score": 92,
          "url": "https://www.youtube.com/watch?v=RwQPMHZHsY0"
        },
        {
          "program_id": "24/7 Universe, Physics & Ancient Mysteries 2026-02-20 17:15_program_4",
          "program_name": "24/7 Universe, Physics & Ancient Mysteries 2026-02-20 17:15",
          "start": 1254,
          "end": 1303,
          "genre": "science",
          "score": 105,
          "url": "https://www.youtube.com/watch?v=RwQPMHZHsY0"
        },
        {
          "program_id": "24/7 Universe, Physics & Ancient Mysteries 2026-02-20 17:15_program_5",
          "program_name": "24/7 Universe, Physics & Ancient Mysteries 2026-02-20 17:15",
          "start": 1303,
          "end": 1361,
          "genre": "science",
          "score": 88,
          "url": "https://www.youtube.com/watch?v=RwQPMHZHsY0"
        },
        {
          "program_id": "24/7 Universe, Physics & Ancient Mysteries 2026-02-20 17:15_program_6",
          "program_name": "24/7 Universe, Physics & Ancient Mysteries 2026-02-20 17:15",
          "start": 1361,
          "end": 1397,
          "genre": "science",
          "score": 99,
          "url": "https://www.youtube.com/watch?v=RwQPMHZHsY0"
        },
        {
          "program_id": "24/7 Universe, Physics & Ancient Mysteries 2026-02-20 17:15_program_7",
          "program_name": "24/7 Universe, Physics & Ancient Mysteries 2026-02-20 17:15",
          "start": 1397,
          "end": 1430,
          "genre": "science",
          "score": 105,
          "url": "https://www.youtube.com/watch?v=RwQPMHZHsY0"
        }
      ]
    }
  ]
}