{
  "opening_time": 875,
  "closing_time": 1430,
  "min_duration": 35,
  "max_consecutive_genre": 10,
  "channels_count": 2,
  "switch_penalty": 9,
  "termination_penalty": 20,
  "priority_blocks": [],
  "time_preferences": [],
  "channels": [
    {
      "channel_id": 3,
      "channel_name": "Dream Trips",
      "programs": [
        {
          "program_id": "Dream Trips_program_0",
          "program_name": "NASA Cameras Just Caught This on the ISS Live Feed",
          "start": 875,
          "end": 913,
          "genre": "technology",
          "score": 93,
          "url": "https://www.youtube.com/watch?v=kWRhLLbLFE0"
        },
        {
          "program_id": "Dream Trips_program_1",
          "program_name": "NASA Cameras Just Caught This on the ISS Live Feed",
          "start": 913,
          "end": 964,
          "genre": "technology",
          "score": 93,
          "url": "https://www.youtube.com/watch?v=kWRhLLbLFE0"
        },
        {
          "program_id": "Dream Trips_program_2",
          "program_name": "NASA Cameras Just Caught This on the ISS Live Feed",
          "start": 964,
          "end": 1033,
          "genre": "technology",
          "score": 88,
          "url": "https://www.youtube.com/watch?v=kWRhLLbLFE0"
        },
        {
          "program_id": "Dream Trips_program_3",
          "program_name": "NASA Cameras Just Caught This on the ISS Live Feed",
          "start": 1033,
          "end": 1069,
          "genre": "technology",
          "score": 95,
          "url": "https://www.youtube.com/watch?v=kWRhLLbLFE0"
        },
        {
          "program_id": "Dream Trips_program_4",
          "program_name": "NASA Cameras Just Caught This on the ISS Live Feed",
          "start": 1069,
          "end": 1104,
          "genre": "technology",
          "score": 77,
          "url": "https://www.youtube.com/watch?v=kWRhLLbLFE0"
        },
        {
          "program_id": "Dream Trips_program_5",
          "program_name": "NASA Cameras Just Caught This on the ISS Live Feed",
          "start": 1104,
          "end": 1179,
          "genre": "technology",
          "score": 89,
          "url": "https://www.youtube.com/watch?v=kWRhLLbLFE0"
        },
        {
          "program_id": "Dream Trips_program_6",
          "program_name": "NASA Cameras Just Caught This on the ISS Live Feed",
          "start": 1179,
          "end": 1222,
          "genre": "technology",
          "score": 87,
          "url": "https://www.youtube.com/watch?v=kWRhLLbLFE0"
        },
        {
          "program_id": "Dream Trips_program_7",
          "program_name": "NASA Cameras Just Caught This on the ISS Live Feed",
          "start": 1222,
          "end": 1272,
          "genre": "technology",
          "score": 83,
          "url": "https://www.youtube.com/watch?v=kWRhLLbLFE0"
        },
        {
          "program_id": "Dream Trips_program_8",
          "program_name": "NASA Cameras Just Caught This on the ISS Live Feed",
          "start": 1272,
          "end": 1324,
          "genre": "technology",
          "score": 80,
          "url": "https://www.youtube.com/watch?v=kWRhLLbLFE0"
        },
        {
          "program_id": "Dream Trips_program_9",
          "program_name": "NASA Cameras Just Caught This on the ISS Live Feed",
          "start": 1324,
          "end": 1382,
          "genre": "technology",
          "score": 85,
          "url": "https://www.youtube.com/watch?v=kWRhLLbLFE0"
        },
        {
          "program_id": "Dream Trips_program_10",
          "program_name": "NASA Cameras Just Caught This on the ISS Live Feed",
          "start": 1382,
          "end": 1430,
          "genre": "technology",
          "score": 77,
          "url": "https://www.youtube.com/watch?v=kWRhLLbLFE0"
        }
      ]
    }
  ]
}